Metadata-Version: 2.1
Name: fia
Version: 0.2.0
Summary: fia (financial analyzer) package for Python.
Author-email: Aleksey Ustinov <augithub@zohomail.com>
License:                                 Apache License
Project-URL: Homepage, https://github.com/lexust1/fia
Project-URL: Bug Tracker, https://github.com/lexust1/fia/issues
Project-URL: Source Code, https://github.com/lexust1/fia
Keywords: finance,portfolio,trading,crypto,TradingView,AlphaVantage
Classifier: Programming Language :: Python :: 3
Classifier: Operating System :: OS Independent
Classifier: Framework :: Jupyter :: JupyterLab
Classifier: Development Status :: 2 - Pre-Alpha
Classifier: Natural Language :: English
Requires-Python: >=3.10
Provides-Extra: test
License-File: LICENSE
